{
  "setting": {
    "es6": true,
    "postcss": true,
    "minified": false,
    "uglifyFileName": false,
    "enhance": false,
    "packNpmRelationList": [],
    "babelSetting": {
      "ignore": [],
      "disablePlugins": [],
      "outputPath": ""
    },
    "useCompilerPlugins": false,
    "minifyWXML": false,
    "ignoreUploadUnusedFiles": true,
    "packNpmManually": false,
    "condition": false,
    "nodeModules": false
  },
  "compileType": "miniprogram",
  "simulatorPluginLibVersion": {},
  "packOptions": {
    "ignore": [],
    "include": []
  },
  "appid": "wxc32b07183436d962",
  "editorSetting": {}
}